Metadata-Version: 1.1
Name: memedict
Version: 1.0.2
Summary: Knowyourmeme.com definitions scraper
Home-page: https://github.com/KraYmer/memedict
Author: Fabrice Laporte
Author-email: kraymer@gmail.com
License: MIT
Keywords: Know Your Meme desciptions web scraper.
Platform: ALL
Classifier: License :: OSI Approved :: MIT License
Classifier: Programming Language :: Python
Classifier: Topic :: Communications :: Chat
